pypi_security_check/package_data.dat
pypi_security_check/__init__.py
pypi_security_check-1.4.dist-info/METADATA
pypi_security_check-1.4.dist-info/metadata.json
pypi_security_check-1.4.dist-info/DESCRIPTION.rst
pypi_security_check-1.4.dist-info/entry_points.txt
pypi_security_check-1.4.dist-info/top_level.txt
pypi_security_check-1.4.dist-info/RECORD
pypi_security_check-1.4.dist-info/WHEEL
