Metadata-Version: 2.0
Name: pypi-security-check
Version: 1.4
Summary: A test of PyPi security
Home-page: https://github.com/andrewpollock/pypi_security_check
Author: Andrew Pollock
Author-email: andrew@pollock.id.au
License: MIT
Keywords: security
Platform: UNKNOWN
Classifier: Development Status :: 3 - Alpha
Classifier: Intended Audience :: Developers
Classifier: Topic :: Software Development :: Build Tools
Classifier: License :: OSI Approved :: MIT License
Classifier: Programming Language :: Python :: 2
Classifier: Programming Language :: Python :: 2.6
Classifier: Programming Language :: Python :: 2.7
Classifier: Programming Language :: Python :: 3
Classifier: Programming Language :: Python :: 3.3
Classifier: Programming Language :: Python :: 3.4
Classifier: Programming Language :: Python :: 3.5
Provides-Extra: dev
Requires-Dist: check-manifest; extra == 'dev'
Provides-Extra: test
Requires-Dist: coverage; extra == 'test'
